aioseaweedfs/__init__.py
aioseaweedfs/api.py
aioseaweedfs-0.3.1.dist-info/LICENSE
aioseaweedfs-0.3.1.dist-info/METADATA
aioseaweedfs-0.3.1.dist-info/WHEEL
aioseaweedfs-0.3.1.dist-info/top_level.txt
aioseaweedfs-0.3.1.dist-info/zip-safe
aioseaweedfs-0.3.1.dist-info/RECORD
